gfagraphs/__init__.py
gfagraphs/abstractions.py
gfagraphs/gfaparser.py
gfagraphs/graph.py
gfagraphs/nx.py
gfagraphs-0.3.20.dist-info/licenses/LICENSE
gfagraphs-0.3.20.dist-info/METADATA
gfagraphs-0.3.20.dist-info/WHEEL
gfagraphs-0.3.20.dist-info/top_level.txt
gfagraphs-0.3.20.dist-info/RECORD
