Metadata-Version: 2.4
Name: gfagraphs
Version: 0.3.20
Summary: Library to parse, edit and handle in memory GFA graphs
Home-page: https://github.com/dubbsieg/gfagraphs
Author: ('Siegfried Dubois',)
Author-email: Siegfried Dubois <siegfried.dubois@inria.fr>
Project-URL: Homepage, https://github.com/dubbsieg/gfagraphs
Project-URL: Bug Tracker, https://github.com/dubbsieg/gfagraphs/issues
Classifier: Programming Language :: Python :: 3
Classifier: Operating System :: OS Independent
Requires-Python: >=3.10
License-File: LICENSE
Dynamic: author
Dynamic: home-page
Dynamic: license-file
